codeinsight/__init__.py
codeinsight/cli.py
codeinsight/scanner.py
codeinsight/watcher.py
codeinsight/ai/__init__.py
codeinsight/ai/analyzer.py
codeinsight/ai/anthropic_provider.py
codeinsight/ai/base.py
codeinsight/ai/factory.py
codeinsight/ai/google_provider.py
codeinsight/ai/models.py
codeinsight/ai/ollama_provider.py
codeinsight/ai/openai_provider.py
codeinsight/ai/qwen_provider.py
codeinsight/analysis/__init__.py
codeinsight/analysis/advanced_duplicates.py
codeinsight/analysis/comparator.py
codeinsight/analysis/refactor_plan_generator.py
codeinsight/analysis/smells.py
codeinsight/analysis/tech_stack_detector.py
codeinsight/analysis/tech_stack_runner.py
codeinsight/analyzers/__init__.py
codeinsight/analyzers/complexity.py
codeinsight/analyzers/line_counter.py
codeinsight/analyzers/unused_code.py
codeinsight/analyzers/unused_files.py
codeinsight/config/__init__.py
codeinsight/config/manager.py
codeinsight/config/models.py
codeinsight/exporters/__init__.py
codeinsight/exporters/csv_exporter.py
codeinsight/exporters/html_exporter.py
codeinsight/exporters/json_exporter.py
codeinsight/models/__init__.py
codeinsight/models/metrics.py
codeinsight/utils/__init__.py
codeinsight/utils/gitignore.py
refactoroscope-0.4.1.dist-info/licenses/LICENSE
refactoroscope-0.4.1.dist-info/METADATA
refactoroscope-0.4.1.dist-info/WHEEL
refactoroscope-0.4.1.dist-info/entry_points.txt
refactoroscope-0.4.1.dist-info/top_level.txt
refactoroscope-0.4.1.dist-info/RECORD
