Metadata-Version: 2.4
Name: refactoroscope
Version: 0.4.1
Summary: A Python-based command-line tool that provides comprehensive analysis of source code repositories
Home-page: https://github.com/moinsen-dev/refactoroscope
Author: Moinsen Dev
Author-email: Refactoroscope Team <refactoroscope@example.com>
License: MIT
Classifier: Development Status :: 3 - Alpha
Classifier: Intended Audience :: Developers
Classifier: License :: OSI Approved :: MIT License
Classifier: Operating System :: OS Independent
Classifier: Programming Language :: Python :: 3
Classifier: Programming Language :: Python :: 3.13
Requires-Python: >=3.13
License-File: LICENSE
Requires-Dist: rich>=14.1.0
Requires-Dist: radon>=6.0.1
Requires-Dist: pygments>=2.19.2
Requires-Dist: pydantic>=2.11.9
Requires-Dist: typer>=0.17.4
Requires-Dist: lizard>=1.17.31
Requires-Dist: flake8>=7.3.0
Requires-Dist: pandas>=2.3.2
Requires-Dist: jinja2>=3.1.6
Requires-Dist: openpyxl>=3.1.5
Requires-Dist: pathspec>=0.12.1
Requires-Dist: pyyaml>=6.0.2
Requires-Dist: watchdog>=6.0.0
Requires-Dist: networkx>=3.5
Requires-Dist: openai>=1.107.3
Requires-Dist: anthropic>=0.67.0
Requires-Dist: google-generativeai>=0.8.5
Dynamic: author
Dynamic: home-page
Dynamic: license-file
Dynamic: requires-python
